simplification/__init__.py
simplification/cutil.cpython-312-x86_64-linux-gnu.so
simplification/cutil.pyx
simplification/header.h
simplification/librdp.so
simplification/rdp_p.pxd
simplification/stdbool.h
simplification/util.py
simplification-0.7.14.dist-info/METADATA
simplification-0.7.14.dist-info/WHEEL
simplification-0.7.14.dist-info/top_level.txt
simplification-0.7.14.dist-info/RECORD
simplification-0.7.14.dist-info/licenses/LICENSE.md
