Metadata-Version: 2.4
Name: simplification
Version: 0.7.14
Summary: Fast linestring simplification using RDP or Visvalingam-Whyatt and a Rust binary
Author-email: Stephan Hügel <urschrei@gmail.com>
License-Expression: BlueOak-1.0.0
Project-URL: Repository, https://github.com/urschrei/simplification
Project-URL: Tracker, https://github.com/urschrei/simplification/issues
Keywords: Geo,Polyline,Linestring,Ramer-Douglas-Peucker,Douglas-Peucker,Visvalingam-Whyatt
Classifier: Programming Language :: Python
Classifier: Programming Language :: Python :: 3.10
Classifier: Programming Language :: Python :: 3.11
Classifier: Programming Language :: Python :: 3.12
Classifier: Programming Language :: Python :: 3.13
Classifier: Programming Language :: Python :: 3.14
Classifier: Development Status :: 5 - Production/Stable
Classifier: Intended Audience :: Developers
Classifier: Intended Audience :: Science/Research
Classifier: Intended Audience :: Education
Classifier: Operating System :: OS Independent
Classifier: Topic :: Software Development :: Libraries :: Python Modules
Classifier: Topic :: Scientific/Engineering :: GIS
Requires-Python: >=3.10
License-File: LICENSE.md
Requires-Dist: numpy>=2.0.0
Provides-Extra: test
Requires-Dist: pytest>=7.4.2; extra == "test"
Dynamic: license-file
